google/cloud/documentai/__init__.py
google/cloud/documentai/gapic_version.py
google/cloud/documentai/py.typed
google/cloud/documentai_v1/__init__.py
google/cloud/documentai_v1/gapic_metadata.json
google/cloud/documentai_v1/gapic_version.py
google/cloud/documentai_v1/py.typed
google/cloud/documentai_v1/services/__init__.py
google/cloud/documentai_v1/services/document_processor_service/__init__.py
google/cloud/documentai_v1/services/document_processor_service/async_client.py
google/cloud/documentai_v1/services/document_processor_service/client.py
google/cloud/documentai_v1/services/document_processor_service/pagers.py
google/cloud/documentai_v1/services/document_processor_service/transports/__init__.py
google/cloud/documentai_v1/services/document_processor_service/transports/base.py
google/cloud/documentai_v1/services/document_processor_service/transports/grpc.py
google/cloud/documentai_v1/services/document_processor_service/transports/grpc_asyncio.py
google/cloud/documentai_v1/services/document_processor_service/transports/rest.py
google/cloud/documentai_v1/services/document_processor_service/transports/rest_base.py
google/cloud/documentai_v1/types/__init__.py
google/cloud/documentai_v1/types/barcode.py
google/cloud/documentai_v1/types/document.py
google/cloud/documentai_v1/types/document_io.py
google/cloud/documentai_v1/types/document_processor_service.py
google/cloud/documentai_v1/types/document_schema.py
google/cloud/documentai_v1/types/evaluation.py
google/cloud/documentai_v1/types/geometry.py
google/cloud/documentai_v1/types/operation_metadata.py
google/cloud/documentai_v1/types/processor.py
google/cloud/documentai_v1/types/processor_type.py
google/cloud/documentai_v1beta3/__init__.py
google/cloud/documentai_v1beta3/gapic_metadata.json
google/cloud/documentai_v1beta3/gapic_version.py
google/cloud/documentai_v1beta3/py.typed
google/cloud/documentai_v1beta3/services/__init__.py
google/cloud/documentai_v1beta3/services/document_processor_service/__init__.py
google_cloud_documentai-3.5.0.dist-info/LICENSE
google_cloud_documentai-3.5.0.dist-info/METADATA
google_cloud_documentai-3.5.0.dist-info/WHEEL
google_cloud_documentai-3.5.0.dist-info/top_level.txt
google_cloud_documentai-3.5.0.dist-info/RECORD
